modeltool/__init__.py
modeltool/cf_import_things.py
modeltool/command.py
modeltool/lambda_creator.py
modeltool/lambda_deployer.py
modeltool/parts.py
modeltool/pip_util.py
modeltool/stack_tool.py
modeltool/template_creator.py
modeltool/utility.py
modeltool/template/template_template
modeltool/template/service/.modeltool
modeltool/template/service/database.py
modeltool/template/service/main.py
modeltool/template/service/read_model.py
modeltool/template/service/requirements.txt
modeltool/template/service/config/dev/function.properties
modeltool/template/service/models/YOUR_REAL_MODEL.pkl
modeltool/template/service/utility/__init__.py
modeltool/template/service/utility/tools.py
modeltool/template/simple/.modeltool
modeltool/template/simple/main.py
modeltool/template/simple/requirements.txt
modeltool/template/simple/utility.py
modeltool/template/simple/config/config.ini
modeltool/template/simple/config/dev/function.properties
modeltool/template/simple/config/prod/function.properties
ModelTool-0.8.5.dist-info/LICENSE
ModelTool-0.8.5.dist-info/METADATA
ModelTool-0.8.5.dist-info/WHEEL
ModelTool-0.8.5.dist-info/entry_points.txt
ModelTool-0.8.5.dist-info/top_level.txt
ModelTool-0.8.5.dist-info/RECORD
